amqp10_codec/__init__.py
amqp10_codec/amqp_read_wire_formatting.py
amqp10_codec/amqp_write_wire_formatting.py
amqp10_codec/annotations.py
amqp10_codec/application_properties.py
amqp10_codec/data.py
amqp10_codec/described_format_code.py
amqp10_codec/format_code_consts.py
amqp10_codec/header.py
amqp10_codec/map.py
amqp10_codec/message.py
amqp10_codec/properties.py
amqp10_codec_faster/__init__.py
amqp10_codec_faster/message_faster.c
amqp10_codec_faster/message_faster.cpython-310-x86_64-linux-gnu.so
amqp10_codec_faster/message_faster.html
amqp10_codec_faster/message_faster.pxd
amqp10_codec_faster/message_faster.pyx
amqp10_codec-0.1.7.dist-info/LICENSE
amqp10_codec-0.1.7.dist-info/WHEEL
amqp10_codec-0.1.7.dist-info/METADATA
amqp10_codec-0.1.7.dist-info/RECORD
