Metadata-Version: 2.1
Name: amqp10-codec
Version: 0.1.7
Summary: 
Author: Gabriele Santomaggio
Author-email: G.santomaggio@gmail.com
Requires-Python: >=3.6,<4.0
Classifier: Programming Language :: Python :: 3
Classifier: Programming Language :: Python :: 3.10
Classifier: Programming Language :: Python :: 3.6
Classifier: Programming Language :: Python :: 3.7
Classifier: Programming Language :: Python :: 3.8
Classifier: Programming Language :: Python :: 3.9
